Verilog Implementation/Carry Look-Ahead Adder/CLA.v
`timescale 1ns/1ps
module CLA (
    input [3:0] a,
    input [3:0] b,
    input Cin,
    output reg [3:0] sum,
    output reg [3:0] C_out
);
    reg [3:0] p;
    reg [3:0] g;
    always @(*) begin
        //Propagate   pi = ai xor bi
        p[0] = a[0] ^ b[0];
        p[1] = a[1] ^ b[1];
        p[2] = a[2] ^ b[2];
        p[3] = a[3] ^ b[3];
        //Generate    gi = ai and bi
        g[0] = a[0] & b[0];
        g[1] = a[1] & b[1];
        g[2] = a[2] & b[2];
        g[3] = a[3] & b[3];
        //Carry-Out   c(i+1) = (pi and ci) + gi
        C_out[0] = (p[0] & Cin) | g[0];
        C_out[1] = (p[1] & C_out[0]) | g[1];
        C_out[2] = (p[2] & C_out[1]) | g[2];
        C_out[3] = (p[3] & C_out[2]) | g[3];
        //Sum       sum_i = pi xor ci
        sum[0] = p[0] ^ Cin;
        sum[1] = p[1] ^ C_out[0];
        sum[2] = p[2] ^ C_out[1];
        sum[3] = p[3] ^ C_out[2];
    end


        // //Propagate   pi = ai xor bi
        // assign p[0] = a[0] ^ b[0];
        // assign p[1] = a[1] ^ b[1];
        // assign p[2] = a[2] ^ b[2];
        // assign p[3] = a[3] ^ b[3];
        // //Generate    gi = ai and bi
        // assign g[0] = a[0] & b[0];
        // assign g[1] = a[1] & b[1];
        // assign g[2] = a[2] & b[2];
        // assign g[3] = a[3] & b[3];
        // //Carry-Out   c(i+1) = (pi and ci) + gi
        // assign C_in[0] = Cin;
        // assign C_in[1] = (p[0] & C_out[0]) & g[0];
        // assign C_in[2] = (p[2] & C_out[1]) & g[2];
        // assign C_in[3] = (p[3] & C_out[2]) & g[3];
        
        // //Sum       sum_i = pi xor ci
        // assign sum[0] = p[0] ^ C_in[0];
        // assign sum[1] = p[1] ^ C_in[1];
        // assign sum[2] = p[2] ^ C_in[2];
        // assign sum[3] = p[3] ^ C_in[3];
endmodule

Verilog Implementation/Wrapper.v
`timescale 1ns/1ps
module FF (
    input [3:0] a,
    input [3:0] b,
    input clk,
    output reg [3:0] C_out,
    output reg [3:0] sum

);
    reg Cin;
    wire [3:0] Q_C_out;
    wire [3:0] Q_sum;
    reg [3:0] Q_a;
    reg [3:0] Q_b;
    initial Cin = 0; 

    //Flip-flop for A
    always @(posedge clk) begin
        Q_a = a;
    end
    //Flip-flop for B
    always @(posedge clk) begin
        Q_b = b;
    end
    // D_FF fpA(.D(a),
    //         .clk(clk),
    //         .Q(Q_b));

    // D_FF fpB(.D(b),
    //         .clk(clk),
    //         .Q(Q_b));

    CLA cl(.a(Q_a),
            .b(Q_b),
            .Cin(Cin),
            .sum(Q_sum),
            .C_out(Q_C_out));

    // D_FF fpSum(.D(Q_sum),
    //         .clk(clk),
    //         .Q(sum));

    // D_FF fpCarry(.D(Q_C_out),
    //         .clk(clk),
    //         .Q(C_out));

    //Flip-flop for Carry-Out
    always @(posedge clk) begin
        C_out = Q_C_out;
    end
    //Flip
    always @(posedge clk) begin
        sum = Q_sum;
    end
endmodule

Verilog Implementation/Carry Look-Ahead Adder/tb_CLA.v
`timescale 1ns/1ps
module tb;
    reg [3:0] a;
    reg [3:0] b;
    wire [3:0] sum;
    wire [3:0] C_out;
    reg clk;
    wire [3:0] Q_a;
    wire [3:0] Q_b;

    FF CLA_timed(.a(a),
                .b(b),
                .clk(clk),
                .C_out(C_out),
                .sum(sum));

initial clk = 1;
    initial begin
      $monitor("\ta=%d,b=%dsum=%d,cout=%d,",a,b,sum,C_out[3]);
        $dumpfile("DUMP_CLA.vcd");
     	$dumpvars(0,tb);
		a = 0;
		b = 0;
        #10 a = 4'd3; b = 4'd2;
        #20 a = 4'd7; b = 4'd2; 
        #20 a = 4'd2; b = 4'd13;
        #20 a = 4'd2; b = 4'd2;
        #20 a = 4'd4; b = 4'd8; 
        #20 a = 4'd3; b = 4'd13;
        #20 a = 4'd5; b = 4'd6;
        #20;
        #20;
        $finish;
	end

        always #10 clk = ~clk;
endmodule

Verilog Implementation/Carry Look-Ahead Adder/DUMP_CLA.vcd
$date
	Thu Apr 29 12:20:56 2021
$end
$version
	Icarus Verilog
$end
$timescale
	1ps
$end
$scope module tb $end
$var wire 4 ! sum [3:0] $end
$var wire 4 " C_out [3:0] $end
$var reg 4 # a [3:0] $end
$var reg 4 $ b [3:0] $end
$var reg 1 % clk $end
$scope module CLA_timed $end
$var wire 4 & a [3:0] $end
$var wire 4 ' b [3:0] $end
$var wire 1 % clk $end
$var wire 4 ( Q_sum [3:0] $end
$var wire 4 ) Q_C_out [3:0] $end
$var reg 4 * C_out [3:0] $end
$var reg 1 + Cin $end
$var reg 4 , Q_a [3:0] $end
$var reg 4 - Q_b [3:0] $end
$var reg 4 . sum [3:0] $end
$scope module cl $end
$var wire 1 + Cin $end
$var wire 4 / a [3:0] $end
$var wire 4 0 b [3:0] $end
$var reg 4 1 C_out [3:0] $end
$var reg 4 2 g [3:0] $end
$var reg 4 3 p [3:0] $end
$var reg 4 4 sum [3:0] $end
$upscope $end
$upscope $end
$upscope $end
$enddefinitions $end
#0
$dumpvars
b0 4
b0 3
b0 2
b0 1
b0 0
b0 /
bx .
b0 -
b0 ,
0+
bx *
b0 )
b0 (
b0 '
b0 &
1%
b0 $
b0 #
bx "
bx !
$end
#10000
0%
b10 $
b10 '
b11 #
b11 &
#20000
b101 (
b101 4
b10 )
b10 1
b10 2
b1 3
b0 !
b0 .
b0 "
b0 *
b10 -
b10 0
b11 ,
b11 /
1%
#30000
0%
b111 #
b111 &
#40000
b1001 (
b1001 4
b110 )
b110 1
b101 3
b111 ,
b111 /
b10 "
b10 *
b101 !
b101 .
1%
#50000
0%
b1101 $
b1101 '
b10 #
b10 &
#60000
b1111 (
b1111 4
b0 )
b0 1
b0 2
b1111 3
b1001 !
b1001 .
b110 "
b110 *
b1101 -
b1101 0
b10 ,
b10 /
1%
#70000
0%
b10 $
b10 '
#80000
b100 (
b100 4
b10 )
b10 1
b10 2
b0 3
b10 -
b10 0
b0 "
b0 *
b1111 !
b1111 .
1%
#90000
0%
b1000 $
b1000 '
b100 #
b100 &
#100000
b1100 (
b1100 4
b0 )
b0 1
b0 2
b1100 3
b100 !
b100 .
b10 "
b10 *
b1000 -
b1000 0
b100 ,
b100 /
1%
#110000
0%
b1101 $
b1101 '
b11 #
b11 &
#120000
b0 (
b0 4
b1111 )
b1111 1
b1 2
b1110 3
b11 ,
b11 /
b1101 -
b1101 0
b0 "
b0 *
b1100 !
b1100 .
1%
#130000
0%
b110 $
b110 '
b101 #
b101 &
#140000
b1011 (
b1011 4
b100 )
b100 1
b100 2
b11 3
b0 !
b0 .
b1111 "
b1111 *
b110 -
b110 0
b101 ,
b101 /
1%
#150000
0%
#160000
b100 "
b100 *
b1011 !
b1011 .
1%
